setup.py
wsi_prob_distributions/Binomialdistribution.py
wsi_prob_distributions/Gaussiandistribution.py
wsi_prob_distributions/Generaldistribution.py
wsi_prob_distributions/__init__.py
wsi_prob_distributions.egg-info/PKG-INFO
wsi_prob_distributions.egg-info/SOURCES.txt
wsi_prob_distributions.egg-info/dependency_links.txt
wsi_prob_distributions.egg-info/not-zip-safe
wsi_prob_distributions.egg-info/top_level.txt