Metadata-Version: 1.0
Name: wsi-prob-distributions
Version: 0.1
Summary: Gaussian and Binomial distributions
Home-page: UNKNOWN
Author: Walid Ismail
Author-email: UNKNOWN
License: UNKNOWN
Platform: UNKNOWN
